VSPEC/__init__.py
VSPEC/analysis.py
VSPEC/config.py
VSPEC/geometry.py
VSPEC/main.py
VSPEC/psg_api.py
VSPEC/data/molec.json
VSPEC/gcm/__init__.py
VSPEC/gcm/heat_transfer.py
VSPEC/gcm/twoface.py
VSPEC/helpers/__init__.py
VSPEC/helpers/astropy_units.py
VSPEC/helpers/files.py
VSPEC/helpers/misc.py
VSPEC/helpers/teff.py
VSPEC/params/__init__.py
VSPEC/params/base.py
VSPEC/params/gcm.py
VSPEC/params/observation.py
VSPEC/params/planet.py
VSPEC/params/read.py
VSPEC/params/stellar.py
VSPEC/presets/earth.yaml
VSPEC/presets/faculae.yaml
VSPEC/presets/flares.yaml
VSPEC/presets/jwst.yaml
VSPEC/presets/proxcenb.yaml
VSPEC/presets/spots.yaml
VSPEC/spectra/__init__.py
VSPEC/spectra/forward.py
vspec-1.1.0.dist-info/licenses/AUTHORS.md
vspec-1.1.0.dist-info/licenses/LICENSE
vspec-1.1.0.dist-info/METADATA
vspec-1.1.0.dist-info/WHEEL
vspec-1.1.0.dist-info/top_level.txt
vspec-1.1.0.dist-info/RECORD
