Metadata-Version: 2.4
Name: VSPEC
Version: 1.1.0
Summary: Simulate Observations of Exoplanets in Variable Star Systems
Author-email: Ted Johnson <ted.johnson@unlv.edu>, Cameron Kelahan <cameron.kelahan@gmail.com>
Maintainer-email: Ted Johnson <ted.johnson@unlv.edu>
License: MIT License
Project-URL: Documentation, https://vspec-collab.github.io/VSPEC/latest/
Project-URL: Repository, https://github.com/VSPEC-collab/VSPEC
Project-URL: Issues, https://github.com/VSPEC-collab/VSPEC/issues
Keywords: exoplanet,astronomy,star
Classifier: Development Status :: 4 - Beta
Classifier: Intended Audience :: Science/Research
Classifier: Topic :: Scientific/Engineering :: Astronomy
Classifier: License :: OSI Approved :: MIT License
Classifier: Programming Language :: Python :: 3
Classifier: Programming Language :: Python :: 3.10
Classifier: Programming Language :: Python :: 3.11
Classifier: Programming Language :: Python :: 3.12
Classifier: Programming Language :: Python :: 3.13
Classifier: Operating System :: OS Independent
Requires-Python: >=3.10
License-File: LICENSE
License-File: AUTHORS.md
Requires-Dist: numpy~=1.26.3
Requires-Dist: astropy
Requires-Dist: scipy
Requires-Dist: tqdm
Requires-Dist: matplotlib
Requires-Dist: pathlib
Requires-Dist: netCDF4
Requires-Dist: pyyaml
Requires-Dist: libpypsg>=0.5.0
Requires-Dist: vspec-vsm~=0.3.7
Requires-Dist: GridPolator~=0.5
Provides-Extra: plot
Requires-Dist: matplotlib; extra == "plot"
Requires-Dist: cartopy; extra == "plot"
Provides-Extra: dev
Requires-Dist: pytest; extra == "dev"
Requires-Dist: pytest-timeout; extra == "dev"
Requires-Dist: pandas; extra == "dev"
Requires-Dist: pep8; extra == "dev"
Requires-Dist: pydata-sphinx-theme; extra == "dev"
Requires-Dist: imageio; extra == "dev"
Requires-Dist: numpydoc; extra == "dev"
Requires-Dist: sphinx; extra == "dev"
Requires-Dist: sphinx-automodapi; extra == "dev"
Requires-Dist: sphinx-gallery; extra == "dev"
Requires-Dist: sphinxcontrib-bibtex; extra == "dev"
Requires-Dist: sphinxcontrib-napoleon; extra == "dev"
Dynamic: license-file
